pokemon_card_recognizer/__init__.py
pokemon_card_recognizer/api/__init__.py
pokemon_card_recognizer/api/card_recognizer.py
pokemon_card_recognizer/api/operating_mode.py
pokemon_card_recognizer/api/test/test_end_to_end.py
pokemon_card_recognizer/api/test/single_images/card.png
pokemon_card_recognizer/api/test/single_images/no_call.png
pokemon_card_recognizer/api/test/video/test.avi
pokemon_card_recognizer/classifier/__init__.py
pokemon_card_recognizer/classifier/core/__init__.py
pokemon_card_recognizer/classifier/core/card_frame_run.py
pokemon_card_recognizer/classifier/core/card_prediction_result.py
pokemon_card_recognizer/classifier/core/rules.py
pokemon_card_recognizer/classifier/core/vocab.py
pokemon_card_recognizer/classifier/core/word_classifier.py
pokemon_card_recognizer/classifier/eval/__init__.py
pokemon_card_recognizer/classifier/eval/sensitivity.py
pokemon_card_recognizer/classifier/test/test_card_prediction_result.py
pokemon_card_recognizer/classifier/test/test_word_classifier.py
pokemon_card_recognizer/eval/__init__.py
pokemon_card_recognizer/eval/eval.py
pokemon_card_recognizer/infra/__init__.py
pokemon_card_recognizer/infra/ptcgsdk/__init__.py
pokemon_card_recognizer/infra/ptcgsdk/ptcgsdk.py
pokemon_card_recognizer/pulls_estimator/__init__.py
pokemon_card_recognizer/pulls_estimator/plots.py
pokemon_card_recognizer/pulls_estimator/pulls_estimator.py
pokemon_card_recognizer/pulls_estimator/pulls_summary.py
pokemon_card_recognizer/pulls_estimator/test/__init__.py
pokemon_card_recognizer/pulls_estimator/test/test_plots.py
pokemon_card_recognizer/pulls_estimator/test/test_pulls_estimator.py
pokemon_card_recognizer/reference/__init__.py
pokemon_card_recognizer/reference/core/__init__.py
pokemon_card_recognizer/reference/core/build.py
pokemon_card_recognizer/reference/core/card_reference.py
pokemon_card_recognizer/reference/data/ref_build/151.pkl
pokemon_card_recognizer/reference/data/ref_build/ancient_origins.pkl
pokemon_card_recognizer-0.0.1.3.8.7.dist-info/METADATA
pokemon_card_recognizer-0.0.1.3.8.7.dist-info/WHEEL
pokemon_card_recognizer-0.0.1.3.8.7.dist-info/licenses/LICENSE
pokemon_card_recognizer-0.0.1.3.8.7.dist-info/RECORD
