Metadata-Version: 2.4
Name: pokemon-card-recognizer
Version: 0.0.1.3.8.7
Summary: Pokemon TCG Card Recognizer
Project-URL: Homepage, https://github.com/prateekt/pokemon-card-recognizer
Project-URL: Bug Tracker, https://github.com/prateekt/pokemon-card-recognizer/issues
Author-email: Prateek Tandon <prateek1.tandon@gmail.com>
License-Expression: GPL-3.0-or-later
License-File: LICENSE
Classifier: License :: OSI Approved :: MIT License
Classifier: Operating System :: OS Independent
Classifier: Programming Language :: Python :: 3
Requires-Python: >=3.11.4
Requires-Dist: bidict
Requires-Dist: ocr-ops
Requires-Dist: ordered-set
Requires-Dist: pandas
Requires-Dist: pillow==9.5.0
Requires-Dist: pokemontcgsdk
Requires-Dist: requests
Requires-Dist: tqdm
